griddly/GymWrapper.py
griddly/RenderTools.py
griddly/__init__.py
griddly-0.0.12.dist-info/METADATA
griddly-0.0.12.dist-info/WHEEL
griddly-0.0.12.dist-info/top_level.txt
griddly-0.0.12.dist-info/RECORD
