Metadata-Version: 2.1
Name: griddly
Version: 0.0.12
Summary: Griddly Python Libraries
Home-page: https://github.com/bam4d/Griddly
Author-email: chrisbam4d@gmail.com
License: UNKNOWN
Platform: UNKNOWN
Requires-Dist: numpy (>=1.19.1)
Requires-Dist: gym (>=0.17.2)
Requires-Dist: opencv-python (>=4.2.0)
